parsnet/__init__.py
parsnet/constraints.py
parsnet-0.1.dist-info/METADATA
parsnet-0.1.dist-info/RECORD
parsnet-0.1.dist-info/WHEEL
parsnet-0.1.dist-info/top_level.txt
